odoo/addons/fieldservice_account/README.rst
odoo/addons/fieldservice_account/__init__.py
odoo/addons/fieldservice_account/__manifest__.py
odoo/addons/fieldservice_account/i18n/de.po
odoo/addons/fieldservice_account/i18n/es.po
odoo/addons/fieldservice_account/i18n/es_AR.po
odoo/addons/fieldservice_account/i18n/es_CL.po
odoo/addons/fieldservice_account/i18n/fieldservice_account.pot
odoo/addons/fieldservice_account/i18n/it.po
odoo/addons/fieldservice_account/i18n/pt_BR.po
odoo/addons/fieldservice_account/i18n/tr.po
odoo/addons/fieldservice_account/models/__init__.py
odoo/addons/fieldservice_account/models/account_move.py
odoo/addons/fieldservice_account/models/account_move_line.py
odoo/addons/fieldservice_account/models/fsm_order.py
odoo/addons/fieldservice_account/models/fsm_stage.py
odoo/addons/fieldservice_account/readme/CONFIGURE.md
odoo/addons/fieldservice_account/readme/CONTRIBUTORS.md
odoo/addons/fieldservice_account/readme/CREDITS.md
odoo/addons/fieldservice_account/readme/DESCRIPTION.md
odoo/addons/fieldservice_account/readme/INSTALL.md
odoo/addons/fieldservice_account/readme/USAGE.md
odoo/addons/fieldservice_account/security/ir.model.access.csv
odoo/addons/fieldservice_account/static/description/icon.png
odoo/addons/fieldservice_account/static/description/index.html
odoo/addons/fieldservice_account/tests/__init__.py
odoo/addons/fieldservice_account/tests/test_fsm_account.py
odoo/addons/fieldservice_account/views/account_move.xml
odoo/addons/fieldservice_account/views/fsm_order.xml
odoo/addons/fieldservice_account/views/fsm_stage.xml
odoo_addon_fieldservice_account-18.0.1.1.0.1.dist-info/METADATA
odoo_addon_fieldservice_account-18.0.1.1.0.1.dist-info/WHEEL
odoo_addon_fieldservice_account-18.0.1.1.0.1.dist-info/top_level.txt
odoo_addon_fieldservice_account-18.0.1.1.0.1.dist-info/RECORD
